Workbook

Sheet PRODUCTOS GENERALES PEYBU 
A1: Code | B1: Name | C1: Cod. Familia / Departamento | D1: Cant. Inventario | E1: Cod. Unidad | F1: Min | G1: Max | H1: Cost | I1: Bar Code | J1: Reorder Point | K1: R. Qty | L1: Waste | M1: Cod. Warehouse | N1: Presentacion del proveedor | O1: Costo Proveedor | P1: Producto Final? (Si,No) | Q1: Precio Venta | R1: Impuesto Item | S1: Cod. Categoria Item | T1: Cod. Item | U1: Cod. Autor | V1: Cod. Colección | W1: Activo? (Si/No) | X1: Descripcion | Y1: Precio Especial | Z1: Caracteristica1 | AA1: Venta Online Ecommerce? (Si/No) | AB1: Nombre de Imagen | AC1: Unidad de Inventario de Producto | AE1: RECEPCION INCIAL
A2: PEY01 | B2: Bolsa plana flexible 43x41 | C2: Empaques | E2: Unidad | H2: 1580 | M2: W100 | N2: Unidad | O2: 12000 | AC2: Unidad | AD2: 10 l | AE2: ALMACEN-COMPRAS
A3: PEY02 | B3: bolsa planaflexible 32x36 | C3: Empaques | E3: Unidad | H3: 1382 | M3: W100 | N3: Unidad | O3: 8000 | P3: No | AC3: Unidad | AD3: 5 l | AE3: ALMACEN-COMPRAS
A4: PEY03 | B4: bolsa para empacar hueso | C4: Empaques | E4: Unidad | H4: 750 | M4: W100 | N4: Unidad | O4: 20000 | P4: SI | AC4: Unidad | AE4: ALMACEN-COMPRAS
A5: PEY04 | B5: Bolsa capucha canastilla | C5: Otros | E5: Unidad | H5: 400 | M5: W100 | N5: Unidad | O5: 25000 | P5: No | AC5: Unidad | AE5: ALMACEN-COMPRAS
A6: PEY05 | B6: Bolsa Jumbo basura verde | C6: Otros | E6: Unidad | H6: 1580 | M6: W100 | N6: Unidad | O6: 18500 | P6: No | AC6: Unidad | AE6: ALMACEN-COMPRAS
A7: PEY06 | B7: Bolsa jumbo bausra negra | C7: Otros | E7: Unidad | H7: 1580 | M7: W100 | N7: Unidad | O7: 12000 | P7: No | AC7: Unidad | AE7: ALMACEN-COMPRAS
A8: PEY07 | B8: Rollo Industrial Cocina | C8: Otros | E8: Unidad | H8: 104000 | M8: W100 | N8: Unidad | O8: 12000 | P8: No | AC8: Unidad | AE8: ALMACEN-COMPRAS
A9: PEY08 | B9: bolsa jumbo blanca | C9: Otros | E9: Unidad | H9: 1580 | M9: W100 | N9: Unidad | O9: 50000 | P9: No | AC9: Unidad | AE9: ALMACEN-COMPRAS
A10: PEY09 | B10: bolsa baño negra | C10: Otros | E10: Unidad | H10: 1580 | M10: W100 | N10: Unidad | O10: 50000 | P10: No | AC10: Unidad | AE10: ALMACEN-COMPRAS
A11: PEY10 | B11: Tortillas Trigo 16 cm | C11: Cereales y harinas | E11: Unidad | H11: 645 | M11: W100 | N11: Unidad | O11: 12000 | P11: No | AC11: Unidad | AE11: PUNTOS DE VENTA
A12: PEY11 | B12: Tortillas Maíz 11x40 | C12: Cereales y harinas | E12: Unidad | H12: 300 | M12: W100 | N12: Unidad | O12: 2000 | P12: No | AC12: Unidad | AE12: ROGELIOS Y EVENTOS
A13: PEY12 | B13: Queso doblecrema | C13: lacteos | E13: Gramos | H13: 22.6 | M13: W100 | N13: Gramos | O13: 1000 | P13: No | AC13: Gramos | AE13: AUTOCAR Y EVENTOS
A14: PEY13 | B14: Tortillas Trigo 12 cm | C14: Cereales y harinas | E14: Unidad | H14: 642 | M14: W100 | N14: Unidad | AC14: Unidad | AE14: AUTOCAR Y EVENTOS
A15: PEY14 | B15: Tortillas Trigo 22 cm | C15: Cereales y harinas | E15: Unidad | H15: 900 | M15: W100 | N15: Unidad | AC15: Unidad | AE15: AUTOCAR Y EVENTOS
A16: PEY15 | B16: Tortillas fresca Maíz 11x32 autocar | C16: Cereales y harinas | E16: Unidad | H16: 350 | M16: W100 | N16: Unidad | AC16: Unidad | AE16: AUTOCAR Y EVENTOS
A17: PEY16 | B17: cebolla morada | C17: Vegetales y Hortalizas | E17: Gramos | H17: 6 | M17: W100 | N17: Gramos | AC17: Gramos | AE17: ROGELIOS Y EVENTOS
A18: PEY17 | B18: Cilantro | C18: Vegetales y Hortalizas | E18: Gramos | H18: 8.5 | M18: W100 | N18: Gramos | AC18: Gramos | AE18: TODOS LOS PUNTOS
A19: PEY18 | B19: Limón Taithy | C19: Vegetales y Hortalizas | E19: Gramos | H19: 5 | M19: W100 | N19: Gramos | AC19: Gramos | AE19: TODOS LOS PUNTOS
A20: PEY19 | B20: Pimenton mixto | C20: Vegetales y Hortalizas | E20: Gramos | H20: 10 | M20: W100 | N20: Gramos | AC20: Gramos | AE20: AUTOCAR Y PLANTA
A21: PEY20 | B21: cebolla blanca | C21: Vegetales y Hortalizas | E21: Gramos | H21: 6 | M21: W100 | N21: Gramos | AC21: Gramos | AE21: AUTOCAR Y PLANTA
A22: PEY21 | B22: Piña | C22: Vegetales y Hortalizas | E22: Gramos | H22: 10 | M22: W100 | N22: Gramos | AC22: Gramos | AE22: AUTOCAR
A23: PEY22 | B23: Tabasco | C23: Especias y condimentos | E23: mililitro | H23: 130 | M23: W100 | N23: mililitro | AC23: mililitro | AE23: ROGELIOS Y EVENTOS
A24: PEY23 | B24: salsa ingelsa fresh | C24: Especias y condimentos | E24: mililitro | H24: 40.677966 | M24: W100 | N24: mililitro | AC24: mililitro | AE24: ROGELIOS Y EVENTOS
A25: PEY24 | B25: sal de chamoy | C25: Especias y condimentos | E25: Gramos | H25: 48.6 | M25: W100 | N25: Gramos | AC25: Gramos | AE25: ROGELIOS Y EVENTOS
... A27: PEY26 | B27: Basukazo | C27: Especias y condimentos | E27: Unidad | H27: 1200 | M27: W100 | N27: Unidad | AC27: Unidad | AE27: ROGELIO
A28: PEY27 | B28: Agua Botella | C28: Bebidas gaseosificadas | E28: Unidad | H28: 1200 | M28: W100 | N28: Unidad | AC28: Unidad
A29: PEY28 | B29: Cerveza Lata | C29: Bebidas gaseosificadas | E29: Unidad | H29: 2820 | M29: W100 | N29: Unidad | AC29: Unidad
A30: PEY29 | B30: Gaseosas Pet | C30: Bebidas gaseosificadas | E30: Unidad | H30: 2500 | M30: W100 | N30: Unidad | AC30: Unidad
A31: PEY30 | B31: Bolsa scraf cubiertos | C31: Empaques | E31: Unidad | H31: 44.03 | M31: W100 | N31: Unidad | AC31: Unidad
A32: PEY31 | B32: Papel parafinado | C32: Empaques | E32: Unidad | H32: 23.9 | M32: W100 | N32: Unidad | AC32: Unidad
A33: PEY32 | B33: Aluminio 300mt | C33: Empaques | E33: Unidad | H33: 251.33333 | M33: W100 | N33: Unidad | AC33: Unidad
A34: PEY33 | B34: Vinipel | C34: Empaques | E34: Unidad | H34: 135000 | M34: W100 | N34: Unidad | AC34: Unidad
A35: PEY34 | B35: Bolsa Camiseta 20 kilos | C35: Empaques | E35: Unidad | H35: 160 | M35: W100 | N35: Unidad | AC35: Unidad
A36: PEY35 | B36: Servilletas | C36: Empaques | E36: Unidad | H36: 29.616667 | M36: W100 | N36: Unidad | AC36: Unidad
A37: PEY36 | B37: Guantes Plasticos | C37: Otros | E37: Unidad | H37: 18.6 | M37: W100 | N37: Unidad | AC37: Unidad
A38: PEY37 | B38: Guantes Nitrilo | C38: Otros | E38: Unidad | H38: 320 | M38: W100 | N38: Unidad | AC38: Unidad
A39: PEY38 | B39: Tapabocas | C39: Otros | E39: Unidad | H39: 165 | M39: W100 | N39: Unidad | AC39: Unidad
... A78: PEY77 | B78: tapa 0,5 | C78: Empaques | E78: Unidad | H78: 80 | M78: W100 | N78: Unidad | AC78: Unidad
A79: PEY78 | B79: Tortilla de maiz 17x40 | C79: Cereales y harinas | E79: Unidad | H79: 20 | N79: Unidad | AC79: Unidad
A80: PEY79 | B80: Tortillas de trigo 14 cm | C80: Cereales y harinas | E80: Unidad | H80: 20 | N80: Unidad | AC80: Unidad
A81: PEY80 | B81: Queso costeño | C81: lacteos | E81: gramos | H81: 1000 | N81: gramos | AC81: gramos
A82: PEY81 | B82: queso mozarella | C82: lacteos | E82: Gramos | H82: 2500 | N82: Gramos | AC82: Gramos
A83: PEY82 | B83: Brazo de cerdo | C83: proteinas | E83: Gramos | H83: 1000 | N83: Gramos | AC83: Gramos
A84: PEY83 | B84: Bondiola de cerdo | C84: proteinas | E84: Gramos | H84: 1000 | N84: Gramos | AC84: Gramos
A85: PEY84 | AC85: Gramos
A86: PEY85 | B86: Tapa Vaso 16 onzas | C86: Empaques | E86: Unidad | H86: 1 | N86: Unidad | AC86: Unidad
A87: PEY86 | B87: Sopero de 4 onzas | C87: Empaques | E87: Unidad | H87: 1 | N87: Unidad
A88: PEY87 | B88: Tapa sopero 4 onzas | C88: Empaques | E88: Unidad | H88: 1 | N88: Unidad
A89: PEY88 | B89: vaso 9 onzas | C89: Empaques | E89: Unidad | H89: 1 | N89: Unidad
A90: PEY89 | B90: tapa vaso 9 onzas | C90: Empaques | E90: Unidad | H90: 1 | N90: Unidad
A91: PEY90 | B91: Takis | C91: Otros | E91: Gramos | H91: 75
A92: PEY91 | B92: Tostacos | C92: Otros | E92: Gramos | H92: 75
A93: PEY92 | B93: Palomitas de maíz | C93: Otros | E93: Gramos | H93: 75
A94: PEY93 | B94: Harina de trigo Az de oros | C94: Otros | E94: Gramos | H94: 500
A95: PEY94 | B95: Curcuma | C95: Otros | E95: Gramos | H95: 500
A96: PEY95 | B96: Papa | C96: Vegetales y Hortalizas | E96: Gramos | H96: 500
A97: PEY96 | B97: Levadura | C97: Otros | E97: Gramos | H97: 500
A98: PEY97 | B98: Huevo | C98: Otros | E98: Unidad | H98: 1
A99: PEY98 | B99: Margarina | C99: Otros | E99: Gramos | H99: 500
A100: PEY99 | B100: Mantequilla | C100: Otros | E100: Gramos | H100: 500
A101: PEY100 | B101: Queso Americano | C101: lacteos | E101: Gramos | H101: 1000
A102: PEY101 | B102: cadera de res | C102: proteinas | E102: Gramos | H102: 1000
A103: PEY102 | B103: Harina promasa Blanca | C103: Otros | E103: Gramos | H103: 500
A104: PEY103
A105: PEY104

Sheet PRODUCTOS PLANTA PRODUCCION
A1: Code | B1: Name | C1: Cod. Familia / Departamento | D1: Cant. Inventario | E1: Cod. Unidad | F1: Min | G1: Max | H1: Cost | I1: Bar Code | J1: Reorder Point | K1: R. Qty | L1: Waste | M1: Cod. Warehouse | N1: Presentacion del proveedor | O1: Costo Proveedor | P1: Producto Final? (Si,No) | Q1: Precio Venta | R1: Impuesto Item | S1: Cod. Categoria Item | T1: Cod. Item | U1: Cod. Autor | V1: Cod. Colección | W1: Activo? (Si/No) | X1: Descripcion | Y1: Precio Especial | Z1: Caracteristica1 | AA1: Venta Online Ecommerce? (Si/No) | AB1: Nombre de Imagen | AC1: Unidad de Inventario de Producto
A2: PR001 | B2: Carne de res (Descargue) | C2: Proteinas | E2: Gramos | H2: 22 | M2: W100 | N2: Gramos | O2: 12000 | P2: No | AC2: Gramos
A3: PR002 | B3: Panceta de cerdo | C3: Proteinas | E3: Gramos | H3: 27 | M3: W100 | N3: Gramos | O3: 8000 | P3: No | AC3: Gramos
A4: PR003 | B4: chicharrón | C4: Proteinas | E4: Gramos | H4: 36 | M4: W100 | N4: Gramos | O4: 20000 | P4: SI | AC4: Gramos
A5: PR004 | B5: Achiote | C5: Especias y condimentos | E5: Gramos | H5: 38 | M5: W100 | N5: Gramos | O5: 25000 | P5: No | AC5: Gramos
A6: PR005 | B6: Aji dulce | C6: Especias y condimentos | E6: Gramos | H6: 20.2 | M6: W100 | N6: Gramos | O6: 18500 | P6: No | AC6: Gramos
A7: PR006 | B7: Ajo | C7: Vegetales y Hortalizas | E7: Gramos | H7: 16 | M7: W100 | N7: Gramos | O7: 12000 | P7: No | AC7: Gramos
A8: PR007 | B8: Caldo de pollo | C8: Especias y condimentos | E8: Gramos | H8: 34 | M8: W100 | N8: Gramos | O8: 12000 | P8: No | AC8: Gramos
A9: PR008 | B9: Caldo de res | C9: Especias y condimentos | E9: Gramos | H9: 37 | M9: W100 | N9: Gramos | O9: 50000 | P9: No | AC9: Gramos
A10: PR009 | B10: Cebolla blanca | C10: Vegetales y Hortalizas | E10: Gramos | H10: 6 | M10: W100 | N10: Gramos | O10: 50000 | P10: No | AC10: Gramos
A11: PR010 | B11: Chile ancho | C11: Especias y condimentos | E11: Gramos | H11: 120 | M11: W100 | N11: Gramos | O11: 12000 | P11: No | AC11: Gramos
A12: PR011 | B12: Chile de arbol | C12: Especias y condimentos | E12: Gramos | H12: 135 | M12: W100 | N12: Gramos | O12: 2000 | P12: No | AC12: Gramos
A13: PR012 | B13: Chile guajillo | C13: Especias y condimentos | E13: Gramos | H13: 131 | M13: W100 | N13: Gramos | O13: 1000 | P13: No | AC13: Gramos
A14: PR013 | B14: Comino | C14: Especias y condimentos | E14: Gramos | H14: 60 | M14: W100 | N14: Gramos | AC14: Gramos
A15: PR014 | B15: Coriandro | C15: Especias y condimentos | E15: Gramos | H15: 44.03 | M15: W100 | N15: Gramos | AC15: Gramos
A16: PR015 | B16: Grasa de pecho | C16: Proteinas | E16: Gramos | H16: 8 | M16: W100 | N16: Gramos | AC16: Gramos
A17: PR016 | B17: tuetano de res | C17: Proteinas | E17: Gramos | H17: 5 | M17: W100 | N17: Gramos | AC17: Gramos
A18: PR017 | B18: hueso de res | C18: Proteinas | E18: Gramos | H18: 4 | M18: W100 | N18: Gramos | AC18: Gramos
A19: PR018 | B19: manteca de cerdo | C19: Proteinas | E19: Gramos | H19: 19 | M19: W100 | N19: Gramos | AC19: Gramos
A20: PR019 | B20: Laurel | C20: Vegetales y Hortalizas | E20: Gramos | H20: 18 | M20: W100 | N20: Gramos | AC20: Gramos
A21: PR020 | B21: canela en polvo | C21: Especias y condimentos | E21: Gramos | H21: 23 | M21: W100 | N21: Gramos | AC21: Gramos
A22: PR021 | B22: color amarillo | C22: Especias y condimentos | E22: Gramos | H22: 9 | M22: W100 | N22: Gramos | AC22: Gramos
A23: PR022 | B23: Oregano en escamas | C23: Especias y condimentos | E23: Gramos | H23: 31 | M23: W100 | N23: Gramos | AC23: Gramos
A24: PR023 | B24: Pimienta entera blanca | C24: Especias y condimentos | E24: Gramos | H24: 69 | M24: W100 | N24: Gramos | AC24: Gramos
A25: PR024 | B25: Pimienta entera negra | C25: Especias y condimentos | E25: Gramos | H25: 63 | M25: W100 | N25: Gramos | AC25: Gramos
... A73: PEY04 | B73: Bolsa capucha canastilla | C73: Empaques | E73: Unidad | H73: 400 | M73: W100 | N73: Unidad | AC73: Unidad
A74: PEY05 | B74: Bolsa Jumbo basura verde | C74: Otros | E74: Unidad | H74: 1580 | M74: W100 | N74: Unidad | P74: SI | AC74: Unidad
A75: PEY06 | B75: Bolsa jumbo bausra negra | C75: Otros | E75: Unidad | H75: 1580 | M75: W100 | N75: Unidad | P75: SI | AC75: Unidad
A76: PEY07 | B76: Rollo Industrial Cocina | C76: Otros | E76: Unidad | H76: 104000 | M76: W100 | N76: Unidad | P76: SI | AC76: Unidad
A77: PEY08 | B77: bolsa jumbo blanca | C77: Otros | E77: Unidad | H77: 1580 | M77: W100 | N77: Unidad | P77: SI | AC77: Unidad
A78: PEY09 | B78: bolsa baño negra | C78: Otros | E78: Unidad | H78: 1580 | M78: W100 | N78: Unidad | P78: SI | AC78: Unidad
A79: PR068 | B79: Color paprika | C79: Especias y condimentos | E79: mililitro | H79: 70 | M79: W100 | N79: mililitro | P79: NO | AC79: mililitro
A80: PR069 | B80: aceite fritol | C80: Aceites y grasas | E80: Gramos | H80: 9.9644 | M80: W100 | N80: mililitro | AC80: mililitro
A81: PR070 | B81: vinagre blanco | C81: Especias y condimentos | E81: mililitro | H81: 5 | M81: W100 | N81: mililitro | AC81: mililitro
A82: PR071 | B82: vinagre manzana | C82: Especias y condimentos | E82: mililitro | H82: 5 | M82: W100 | N82: mililitro | AC82: mililitro
A83: PR072 | B83: cebolla en polvo | C83: Especias y condimentos | E83: Gramos | H83: 26 | M83: W100 | N83: Gramos | AC83: Gramos
A84: PR073 | B84: sirope de maiz | C84: Especias y condimentos | E84: Gramos | H84: 52 | M84: W100 | N84: mililitro | AC84: mililitro
A85: PR074 | B85: caldo camaron | C85: Especias y condimentos | E85: Gramos | H85: 38 | M85: W100 | N85: Gramos | AC85: Gramos
A86: PR075 | B86: acido citrico | C86: Especias y condimentos | E86: Gramos | H86: 7 | M86: W100 | N86: Gramos | AC86: Gramos
A87: PR076 | B87: color fresa | C87: Especias y condimentos | E87: Gramos | H87: 20 | M87: W100 | N87: Gramos | AC87: Gramos
A88: PR077 | B88: passata de cecca clasica | C88: Especias y condimentos | E88: Gramos | H88: 20 | M88: W100 | N88: Gramos | AC88: Gramos
A89: PR078 | B89: concentrado de tomate | C89: Especias y condimentos | E89: Gramos | H89: 54 | M89: W100 | N89: Gramos | AC89: Gramos
A90: PR079 | B90: salsa de ostras | C90: Especias y condimentos | E90: Gramos | H90: 91 | M90: W100 | N90: Gramos | AC90: Gramos
A91: PEY38 | B91: Tapabocas | C91: Otros | E91: Unidad | H91: 200 | M91: W100 | N91: Unidad | AC91: Unidad
A92: PEY37 | B92: Guantes Nitrilo | C92: Otros | E92: Unidad | H92: 212 | M92: W100 | N92: Unidad | P92: SI | AC92: Unidad
A93: PEY64 | B93: pastilla horno verde | C93: Otros | E93: Unidad | H93: 3173 | M93: W100 | N93: Unidad | P93: SI | AC93: Unidad
A94: PEY65 | B94: pastilla horno azul | C94: otros | E94: Unidad | H94: 3570 | M94: W100 | N94: Unidad | P94: SI | AC94: Unidad
A95: PEY45 | B95: Waypoll | C95: Otros | E95: Unidad | H95: 38750 | M95: W100 | N95: Unidad | P95: SI | AC95: Unidad
A96: PR082 | B96: AGUA POTABLE | C96: Otros | E96: mililitro | H96: 0.1 | M96: W100 | N96: mililitro | P96: SI | AC96: mililitro
A97: PR083 | B97: Aceite de Oliva | C97: Aceites y grasas | E97: mililitro | H97: 55 | M97: W100 | N97: mililitro | P97: si | AC97: mililitro
A98: PR084 | B98: Maicena-Fecula de maiz | C98: Otros | E98: Gramos | H98: 22 | M98: W101 | N98: Gramos | AC98: Gramos
A99: PR085 | B99: Goma xantana | C99: Otros | E99: Gramos | H99: 42 | M99: W102 | N99: Gramos | AC99: Gramos
A100: PR086 | B100: Ciruela Pasa desidratada | C100: Otros | E100: Gramos | H100: 22 | M100: W103 | N100: Gramos | AC100: Gramos
A101: PR087 | B101: Albaricoque | C101: Otros | E101: Gramos | H101: 41 | M101: W104 | N101: Gramos | AC101: Gramos
A102: PR088 | B102: Tajin | C102: Otros | E102: Gramos | H102: 15 | M102: W105 | N102: Gramos | AC102: Gramos
A103: PR089 | B103: Apio en polvo | C103: Otros | E103: Gramos | H103: 21 | M103: W106 | N103: Gramos | AC103: Gramos
A104: PR090 | B104: Maiz Blanco | C104: Vegetales y Hortalizas | E104: Gramos | H104: 30000 | N104: Gramos | AC104: Gramos
A105: PR091 | B105: Canoa 1 kilo | C105: Empaques | E105: Unidad | H105: 200

Sheet Items y Modificadores.
A1: Code | B1: Item Name | C1: Open Price? (Si/No) | D1: Sale Price | E1: Bar Code | F1: Category Code | G1: Sub-Category Name | H1: Category Name | I1: Tax | J1: Active? (Si/No) | K1: Commission | L1: Commission Type ($ / %) | M1: Special Price | N1: Allow Ecommerce Sale ? (Si/No) | O1: Ecommerce Sale Price | P1: Description | Q1: Photo Name | R1: Ecommerce Name | S1: Item Type (Normal, Gift Card, Certificado, Abono, Suscripcion, Domicilio, Tarifa de Cuarto) | T1: Ecommerce Category Code | U1: Ecommerce Category Name | V1: Integration Code | W1: Tax on Item | Y1: Modificador 1 | Z1: Opciones de Modificador 1 | AA1: Precio de modificadro 1 | AC1: Modificador 2 | AD1: Opciones de Modificador 2 | AE1: Precio de modificadro 2
A2: M1 | B2: Whisky Singleton | C2: NO | D2: 0 | E2: Whisky | F2: 0 | G2: Whisky | H2: Licores | I2: 7 | J2: 7 | K2: 7 | L2: 7 | M2: 7 | N2: 7 | O2: 7 | W2: 7 | Y2: Whisky Singleton | Z2: Trago | AA2: 12 | AC2: Opciond de Barra | AD2: Con Hielo | AE2: 0
A3: M1 | B3: Whisky Singleton | C3: NO | D3: 0 | G3: Whisky | H3: Licores | I3: 7 | W3: 7 | Y3: Whisky Singleton | Z3: Botella | AA3: 150 | AC3: Opciond de Barra | AD3: Sin Hielo | AE3: 0
A4: M2 | B4: Whisky Sello Negro | C4: NO | D4: 200 | E4: $ 0.00 | F4: Whisky | G4: Whisky | H4: Licores | I4: 7 | W4: 7
A5: M3 | B5: Whisky Macallan Dbcask 18 AÑos | C5: NO | D5: 130 | E5: $ 28,000,000.00 | F5: Whisky | G5: Whisky | H5: Licores | I5: 7 | W5: 7
A6: M4 | B6: Whisly Glenmorangie Quinta Ruba | C6: NO | D6: 80 | E6: $ 550,000.00 | F6: Whisky | G6: Whisky | H6: Licores | I6: 7 | W6: 7
A7: M5 | B7: Whisly Glenmorangie Original | C7: NO | D7: 125 | E7: $ 450,000.00 | F7: Whisky | G7: Whisky | H7: Licores | I7: 7 | W7: 7
A8: M6 | B8: Whisly Glenmorangie Nectar | C8: NO | D8: 120 | E8: $ 650,000.00 | G8: Whisky | H8: Licores | I8: 7 | W8: 7
A9: M7 | B9: Gin Tonic Tanqueray | C9: NO | D9: 12 | E9: Cócteles | F9: 0 | G9: Cocteles | H9: Licores | I9: 7 | W9: 7
A10: M8 | B10: Gin Tonic Hendrics | C10: NO | D10: 12 | E10: $ 55,000.00 | F10: Cócteles | G10: Cocteles | H10: Licores | I10: 7 | W10: 7
A11: M9 | B11: Margarita Premium 2x1 | C11: NO | D11: 12 | E11: $ 50,000.00 | F11: Cócteles | G11: Cocteles | H11: Licores | I11: 7 | W11: 7
A12: M10 | B12: Tizon Kiwi Lychee | C12: NO | D12: 12 | G12: Cocteles | H12: Licores | I12: 7 | W12: 7
A13: M11 | B13: Hamburguesa Especial | C13: NO | D13: 15 | G13: Platos Fuertes | H13: Menu Alimentos | I13: 7 | W13: 7

Sheet Subrecetas (Producciones.)
A2: Codigo | B2: Nombre de la Produccion | C2: Redimiento | D2: unidad | E2: Cod Ingrediente | F2: Ingredientes | G2: Cantidad | H2: Cantidad
A3: SB001 | B3: SALSA TAQUERA ROGELIO | C3: 15 | D3: Litro | E3: ='PRODUCTOS PLANTA PRODUCCION'!A33 -> PR032 | F3: ='PRODUCTOS PLANTA PRODUCCION'!B33 -> Tomatillo | G3: 5000 | H3: gramos
A4: SB001 | B4: SALSA TAQUERA ROGELIO | C4: 15 | D4: Litro | E4: ='PRODUCTOS PLANTA PRODUCCION'!A29 -> PR028 | F4: ='PRODUCTOS PLANTA PRODUCCION'!B29 -> Tomate chonto | G4: 5800 | H4: gramos
A5: SB001 | B5: SALSA TAQUERA ROGELIO | C5: 15 | D5: Litro | E5: ='PRODUCTOS PLANTA PRODUCCION'!A10 -> PR009 | F5: ='PRODUCTOS PLANTA PRODUCCION'!B10 -> Cebolla blanca | G5: 1700 | H5: gramos
A6: SB001 | B6: SALSA TAQUERA ROGELIO | C6: 15 | D6: Litro | E6: ='PRODUCTOS PLANTA PRODUCCION'!A12 -> PR011 | F6: ='PRODUCTOS PLANTA PRODUCCION'!B12 -> Chile de arbol | G6: 35 | H6: gramos
A7: SB001 | B7: SALSA TAQUERA ROGELIO | C7: 15 | D7: Litro | E7: ='PRODUCTOS PLANTA PRODUCCION'!A13 -> PR012 | F7: ='PRODUCTOS PLANTA PRODUCCION'!B13 -> Chile guajillo | G7: 186 | H7: gramos
A8: SB001 | B8: SALSA TAQUERA ROGELIO | C8: 15 | D8: Litro | E8: ='PRODUCTOS PLANTA PRODUCCION'!A35 -> PR034 | F8: ='PRODUCTOS PLANTA PRODUCCION'!B35 -> Chile morita | G8: 85 | H8: gramos
A9: SB001 | B9: SALSA TAQUERA ROGELIO | C9: 15 | D9: Litro | E9: ='PRODUCTOS PLANTA PRODUCCION'!A7 -> PR006 | F9: Ajo | G9: 420 | H9: gramos
A10: SB001 | B10: SALSA TAQUERA ROGELIO | C10: 15 | D10: Litro | E10: ='PRODUCTOS PLANTA PRODUCCION'!A28 -> PR027 | F10: ='PRODUCTOS PLANTA PRODUCCION'!B28 -> Sal común | G10: 250 | H10: gramos
A11: SB001 | B11: SALSA TAQUERA ROGELIO | C11: 15 | D11: Litro | E11: ='PRODUCTOS PLANTA PRODUCCION'!A96 -> PR082 | F11: ='PRODUCTOS PLANTA PRODUCCION'!B96 -> AGUA POTABLE | G11: 2000 | H11: Mililitro
A12: SB001 | B12: SALSA TAQUERA ROGELIO | C12: 15 | D12: Litro | E12: ='PRODUCTOS GENERALES PEYBU '!A2 -> PEY01 | F12: Bolsa plana flexible 43x41 | G12: 1 | H12: unidad
A15: SB002 | B15: SALSA PICANTE | C15: 11 | D15: Litro | E15: ='PRODUCTOS PLANTA PRODUCCION'!A29 -> PR028 | F15: ='PRODUCTOS PLANTA PRODUCCION'!B29 -> Tomate chonto | G15: 3900 | H15: gramos
A16: SB002 | B16: SALSA PICANTE | C16: 11 | D16: Litro | E16: ='PRODUCTOS PLANTA PRODUCCION'!A10 -> PR009 | F16: Cebolla blanca | G16: 1750 | H16: gramos
A17: SB002 | B17: SALSA PICANTE | C17: 11 | D17: Litro | E17: ='PRODUCTOS PLANTA PRODUCCION'!A36 -> PR035 | F17: ='PRODUCTOS PLANTA PRODUCCION'!B36 -> Chile serrano | G17: 320 | H17: gramos
A18: SB002 | B18: SALSA PICANTE | C18: 11 | D18: Litro | E18: ='PRODUCTOS PLANTA PRODUCCION'!A37 -> PR036 | F18: ='PRODUCTOS PLANTA PRODUCCION'!B37 -> Chile abanero | G18: 500 | H18: gramos
A19: SB002 | B19: SALSA PICANTE | C19: 11 | D19: Litro | E19: PRO33 | F19: Chile morita | G19: 140 | H19: gramos
A20: SB002 | B20: SALSA PICANTE | C20: 11 | D20: Litro | E20: ='PRODUCTOS PLANTA PRODUCCION'!A6 -> PR005 | F20: ='PRODUCTOS PLANTA PRODUCCION'!B6 -> Aji dulce | G20: 640 | H20: gramos
A21: SB002 | B21: SALSA PICANTE | C21: 11 | D21: Litro | E21: ='PRODUCTOS PLANTA PRODUCCION'!A7 -> PR006 | F21: ajo | G21: 280 | H21: gramos
A22: SB002 | B22: SALSA PICANTE | C22: 11 | D22: Litro | E22: ='PRODUCTOS PLANTA PRODUCCION'!A28 -> PR027 | F22: sal comun | G22: 250 | H22: gramos
A23: SB002 | B23: SALSA PICANTE | C23: 11 | D23: Litro | E23: ='PRODUCTOS PLANTA PRODUCCION'!A96 -> PR082 | F23: AGUA POTABLE | G23: 3500 | H23: Mililitro
A24: SB002 | B24: SALSA PICANTE | C24: 11 | D24: Litro | E24: PEY01 | F24: Bolsa plana flexible 43x41 | G24: 1 | H24: unidad
A26: SB003 | B26: SALA TAQUERA AUTOCAR | C26: 5 | D26: Litro | E26: ='PRODUCTOS PLANTA PRODUCCION'!A34 -> PR033 | F26: ='PRODUCTOS PLANTA PRODUCCION'!B34 -> Jalapeño verde | G26: 250 | H26: gramos
A27: SB003 | B27: SALA TAQUERA AUTOCAR | C27: 5 | D27: Litro | E27: PR008 | F27: Cebolla blanca | G27: 500 | H27: gramos
A28: SB003 | B28: SALA TAQUERA AUTOCAR | C28: 5 | D28: Litro | E28: PR005 | F28: ajo | G28: 280 | H28: gramos
A29: SB003 | B29: SALA TAQUERA AUTOCAR | C29: 5 | D29: Litro | E29: ='PRODUCTOS PLANTA PRODUCCION'!A11 -> PR010 | F29: Chile ancho | G29: 140 | H29: gramos
A30: SB003 | B30: SALA TAQUERA AUTOCAR | C30: 5 | D30: Litro | E30: ='PRODUCTOS PLANTA PRODUCCION'!A33 -> PR032 | F30: Tomatillo | G30: 1000 | H30: gramos
A31: SB003 | B31: SALA TAQUERA AUTOCAR | C31: 5 | D31: Litro | E31: ='PRODUCTOS PLANTA PRODUCCION'!A29 -> PR028 | F31: Tomate Chonto | G31: 3000 | H31: gramos
A32: SB003 | B32: SALA TAQUERA AUTOCAR | C32: 5 | D32: Litro | E32: ='PRODUCTOS PLANTA PRODUCCION'!A97 -> PR083 | F32: aceite oliva | G32: 120 | H32: mililitros
A33: SB003 | B33: SALA TAQUERA AUTOCAR | C33: 5 | D33: Litro | E33: ='PRODUCTOS PLANTA PRODUCCION'!A28 -> PR027 | F33: sal comun | G33: 3 | H33: gramos
A34: SB003 | B34: SALA TAQUERA AUTOCAR | C34: 5 | D34: Litro | E34: ='PRODUCTOS PLANTA PRODUCCION'!A27 -> PR026 | F34: Pimienta moilda | G34: 36 | H34: gramos
A35: SB003 | B35: SALA TAQUERA AUTOCAR | C35: 5 | D35: Litro | E35: PEY02 | F35: bolsa planaflexible 32x36 | G35: 1 | H35: unidad
A38: SB004 | B38: SALSA VERDE | C38: 4 | D38: Litro | E38: ='PRODUCTOS PLANTA PRODUCCION'!A34 -> PR033 | F38: Jalapeño verde | G38: 3150 | H38: gramos
A39: SB004 | B39: SALSA VERDE | C39: 4 | D39: Litro | E39: PR008 | F39: Cebolla Blanca | G39: 700 | H39: gramos
A40: SB004 | B40: SALSA VERDE | C40: 4 | D40: Litro | E40: PR005 | F40: Ajo | G40: 155 | H40: gramos
A41: SB004 | B41: SALSA VERDE | C41: 4 | D41: Litro | E41: PR026 | F41: Sal | G41: 35 | H41: gramos
A42: SB004 | B42: SALSA VERDE | C42: 4 | D42: Litro | E42: PR025 | F42: Pimienta molida | G42: 15 | H42: gramos
A43: SB004 | B43: SALSA VERDE | C43: 4 | D43: Litro | E43: PRO83 | F43: Aceite oliva | G43: 40 | H43: mililitros
A44: SB004 | B44: SALSA VERDE | C44: 4 | D44: Litro | E44: PR082 | F44: agua | G44: 200 | H44: mililitros
A45: SB004 | B45: SALSA VERDE | C45: 4 | D45: Litro | E45: PEY02 | F45: bolsa planaflexible 32x36 | G45: 1 | H45: unidad
A48: SB005 | B48: SALSA ROJA | C48: 9 | D48: Litros | E48: ='PRODUCTOS PLANTA PRODUCCION'!A12 -> PR011 | F48: chile de arbol | G48: 100 | H48: gramos
A49: SB005 | B49: SALSA ROJA | C49: 9 | D49: Litros | E49: ='PRODUCTOS PLANTA PRODUCCION'!A29 -> PR028 | F49: Tomate chonto | G49: 5000 | H49: gramos
A50: SB005 | B50: SALSA ROJA | C50: 9 | D50: Litros | E50: ='PRODUCTOS PLANTA PRODUCCION'!A10 -> PR009 | F50: cebolla blanca | G50: 2000 | H50: gramos
A51: SB005 | B51: SALSA ROJA | C51: 9 | D51: Litros | E51: =E40 -> PR005 | F51: Ajo | G51: 100 | H51: gramos
A52: SB005 | B52: SALSA ROJA | C52: 9 | D52: Litros | E52: =E41 -> PR026 | F52: Sal | G52: 50 | H52: gramos
A53: SB005 | B53: SALSA ROJA | C53: 9 | D53: Litros | E53: =E42 -> PR025 | F53: =F42 -> Pimienta molida | G53: 20 | H53: gramos
A54: SB005 | B54: SALSA ROJA | C54: 9 | D54: Litros | E54: =E44 -> PR082 | F54: agua | G54: 1500 | H54: mililitros
A55: SB005 | B55: SALSA ROJA | C55: 9 | D55: Litros | E55: PEY01 | F55: Bolsa plana flexible 43x41 | G55: 1 | H55: unidad
A58: SB006 | B58: SALSA MACHA | C58: 7 | D58: litros | E58: ='PRODUCTOS PLANTA PRODUCCION'!A12 -> PR011 | F58: chile arbol | G58: 210 | H58: gramos
A59: SB006 | B59: SALSA MACHA | C59: 7 | D59: litros | E59: =E19 -> PRO33 | F59: chile morita | G59: 60 | H59: gramos
A60: SB006 | B60: SALSA MACHA | C60: 7 | D60: litros | E60: ='PRODUCTOS PLANTA PRODUCCION'!A38 -> PR037 | F60: chile puya | G60: 115 | H60: gramos
A61: SB006 | B61: SALSA MACHA | C61: 7 | D61: litros | E61: ='PRODUCTOS PLANTA PRODUCCION'!A45 -> PR044 | F61: ajonjoli | G61: 250 | H61: gramos
A62: SB006 | B62: SALSA MACHA | C62: 7 | D62: litros | E62: ='PRODUCTOS PLANTA PRODUCCION'!A46 -> PR045 | F62: Mani blanco | G62: 750 | H62: gramos
A63: SB006 | B63: SALSA MACHA | C63: 7 | D63: litros | E63: =E51 -> PR005 | F63: ajo | G63: 1000 | H63: gramos
A64: SB006 | B64: SALSA MACHA | C64: 7 | D64: litros | E64: =E52 -> PR026 | F64: Sal | G64: 50 | H64: gramos
A65: SB006 | B65: SALSA MACHA | C65: 7 | D65: litros | E65: ='PRODUCTOS PLANTA PRODUCCION'!A67 -> PR066 | F65: aceite de maiz | G65: 5000 | H65: gramos
A66: SB006 | B66: SALSA MACHA | C66: 7 | D66: litros | E66: PEY01 | F66: Bolsa plana flexible 43x41 | G66: 1 | H66: unidad
A69: SB007 | B69: ADOBO PASTOR | C69: 13 | D69: Litros | E69: ='PRODUCTOS PLANTA PRODUCCION'!A25 -> PR024 | F69: ='PRODUCTOS PLANTA PRODUCCION'!B25 -> Pimienta entera negra | G69: 90 | H69: gramos
A70: SB007 | B70: ADOBO PASTOR | C70: 13 | D70: Litros | E70: ='PRODUCTOS PLANTA PRODUCCION'!A24 -> PR023 | F70: ='PRODUCTOS PLANTA PRODUCCION'!B24 -> Pimienta entera blanca | G70: 90 | H70: gramos
A71: SB007 | B71: ADOBO PASTOR | C71: 13 | D71: Litros | E71: ='PRODUCTOS PLANTA PRODUCCION'!A14 -> PR013 | F71: comino | G71: 24 | H71: gramos
A72: SB007 | B72: ADOBO PASTOR | C72: 13 | D72: Litros | E72: ='PRODUCTOS PLANTA PRODUCCION'!A26 -> PR025 | F72: ='PRODUCTOS PLANTA PRODUCCION'!B26 -> Pimienta de olor-Jamica | G72: 27 | H72: gramos
A73: SB007 | B73: ADOBO PASTOR | C73: 13 | D73: Litros | E73: ='PRODUCTOS PLANTA PRODUCCION'!A23 -> PR022 | F73: ='PRODUCTOS PLANTA PRODUCCION'!B23 -> Oregano en escamas | G73: 27 | H73: gramos
A74: SB007 | B74: ADOBO PASTOR | C74: 13 | D74: Litros | E74: ='PRODUCTOS PLANTA PRODUCCION'!A83 -> PR072 | F74: cebolla en polvo | G74: 180 | H74: gramos
A75: SB007 | B75: ADOBO PASTOR | C75: 13 | D75: Litros | E75: ='PRODUCTOS PLANTA PRODUCCION'!A22 -> PR021 | F75: color amarillo | G75: 26 | H75: gramos
A76: SB007 | B76: ADOBO PASTOR | C76: 13 | D76: Litros | E76: ='PRODUCTOS PLANTA PRODUCCION'!A42 -> PR041 | F76: sal nitro rosada | G76: 30 | H76: gramos
A77: SB007 | B77: ADOBO PASTOR | C77: 13 | D77: Litros | E77: ='PRODUCTOS PLANTA PRODUCCION'!A21 -> PR020 | F77: canela en polvo | G77: 36 | H77: gramos
A78: SB007 | B78: ADOBO PASTOR | C78: 13 | D78: Litros | E78: =E63 -> PR005 | F78: ajo | G78: 900 | H78: gramos
A79: SB007 | B79: ADOBO PASTOR | C79: 13 | D79: Litros | E79: ='PRODUCTOS PLANTA PRODUCCION'!A11 -> PR010 | F79: chile ancho | G79: 90 | H79: gramos
A80: SB007 | B80: ADOBO PASTOR | C80: 13 | D80: Litros | E80: ='PRODUCTOS PLANTA PRODUCCION'!A13 -> PR012 | F80: chile guajillo | G80: 180 | H80: gramos
A81: SB007 | B81: ADOBO PASTOR | C81: 13 | D81: Litros | E81: ='PRODUCTOS PLANTA PRODUCCION'!A5 -> PR004 | F81: achiote | G81: 300 | H81: gramos
A82: SB007 | B82: ADOBO PASTOR | C82: 13 | D82: Litros | E82: ='PRODUCTOS PLANTA PRODUCCION'!A82 -> PR071 | F82: vinagre manzana | G82: 3600 | H82: gramos
A83: SB007 | B83: ADOBO PASTOR | C83: 13 | D83: Litros | E83: ='PRODUCTOS PLANTA PRODUCCION'!A96 -> PR082 | F83: agua potable | G83: 7200 | H83: mililitros
A84: SB007 | B84: ADOBO PASTOR | C84: 13 | D84: Litros | E84: PEY01 | F84: Bolsa plana flexible 43x41 | G84: 2 | H84: unidad
A87: SB008 | B87: GRASA ROJA | C87: 35 | D87: kilos | E87: ='PRODUCTOS PLANTA PRODUCCION'!A16 -> PR015 | F87: ='PRODUCTOS PLANTA PRODUCCION'!B16 -> Grasa de pecho | G87: 70000 | H87: gramos
A88: SB008 | B88: GRASA ROJA | C88: 35 | D88: kilos | E88: ='PRODUCTOS PLANTA PRODUCCION'!A29 -> PR028 | F88: Tomate chonto | G88: 7000 | H88: gramos
A89: SB008 | B89: GRASA ROJA | C89: 35 | D89: kilos | E89: ='PRODUCTOS PLANTA PRODUCCION'!A13 -> PR012 | F89: chile guajillo | G89: 350 | H89: gramos
A90: SB008 | B90: GRASA ROJA | C90: 35 | D90: kilos | E90: ='PRODUCTOS PLANTA PRODUCCION'!A12 -> PR011 | F90: chile de arbol | G90: 140 | H90: gramos
A91: SB008 | B91: GRASA ROJA | C91: 35 | D91: kilos | E91: ='PRODUCTOS PLANTA PRODUCCION'!A11 -> PR010 | F91: chile ancho | G91: 350 | H91: gramos
A92: SB008 | B92: GRASA ROJA | C92: 35 | D92: kilos | E92: ='PRODUCTOS PLANTA PRODUCCION'!A79 -> PR068 | F92: color paprika | G92: 455 | H92: gramos
A93: SB008 | B93: GRASA ROJA | C93: 35 | D93: kilos | E93: ='PRODUCTOS PLANTA PRODUCCION'!A6 -> PR005 | F93: aji dulce | G93: 500 | H93: gramos
A94: SB008 | B94: GRASA ROJA | C94: 35 | D94: kilos | E94: ='PRODUCTOS PLANTA PRODUCCION'!A5 -> PR004 | F94: achiote | G94: 250 | H94: gramos
A95: SB008 | B95: GRASA ROJA | C95: 35 | D95: kilos | E95: PEY01 | F95: Bolsa plana flexible 43x41 | G95: 4 | H95: unidad
A98: SB009 | B98: TUETANO COCIDO | C98: 2 | D98: kilos | E98: ='PRODUCTOS PLANTA PRODUCCION'!A17 -> PR016 | F98: tuetano de res | G98: 2500 | H98: gramos
A99: SB009 | B99: TUETANO COCIDO | C99: 2 | D99: kilos | E99: ='PRODUCTOS PLANTA PRODUCCION'!A28 -> PR027 | F99: sal | G99: 50 | H99: gramos
A100: SB009 | B100: TUETANO COCIDO | C100: 2 | D100: kilos | E100: PEY02 | F100: Bolsa plana flexible 43x41 | G100: 1 | H100: unidad
A103: SB010 | B103: BIRRIA ROGELIO | C103: 53 | D103: kilos | E103: PR004 | F103: Achiote | G103: 400 | H103: gramos
A104: SB010 | B104: BIRRIA ROGELIO | C104: 53 | D104: kilos | E104: PR005 | F104: aji dulce | G104: 600 | H104: gramos
A105: SB010 | B105: BIRRIA ROGELIO | C105: 53 | D105: kilos | E105: PR006 | F105: ajo | G105: 480 | H105: gramos
A106: SB010 | B106: BIRRIA ROGELIO | C106: 53 | D106: kilos | E106: PR007 | F106: caldo pollo | G106: 200 | H106: gramos
A107: SB010 | B107: BIRRIA ROGELIO | C107: 53 | D107: kilos | E107: PR008 | F107: caldo res | G107: 200 | H107: gramos
A108: SB010 | B108: BIRRIA ROGELIO | C108: 53 | D108: kilos | E108: PR009 | F108: cebolla blanca | G108: 1600 | H108: gramos
A109: SB010 | B109: BIRRIA ROGELIO | C109: 53 | D109: kilos | E109: PR010 | F109: chile ancho | G109: 640 | H109: gramos
A110: SB010 | B110: BIRRIA ROGELIO | C110: 53 | D110: kilos | E110: PR011 | F110: chile arbol | G110: 48 | H110: gramos
A111: SB010 | B111: BIRRIA ROGELIO | C111: 53 | D111: kilos | E111: PR012 | F111: chile guajillo | G111: 800 | H111: gramos
A112: SB010 | B112: BIRRIA ROGELIO | C112: 53 | D112: kilos | E112: PR013 | F112: comino | G112: 8 | H112: gramos
A113: SB010 | B113: BIRRIA ROGELIO | C113: 53 | D113: kilos | E113: PR014 | F113: coriandro | G113: 32 | H113: gramos
... A135: SB011 | B135: CALDO BIRRIA | C135: 120 | D135: Litros | E135: PR014 | F135: coriandro | G135: 56 | H135: gramos
A136: SB011 | B136: CALDO BIRRIA | C136: 120 | D136: Litros | E136: ='PRODUCTOS PLANTA PRODUCCION'!A16 -> PR015 | F136: grasa de pecho | G136: 7200 | H136: gramos
A137: SB011 | B137: CALDO BIRRIA | C137: 120 | D137: Litros | E137: PR019 | F137: laurel | G137: 32 | H137: gramos
A138: SB011 | B138: CALDO BIRRIA | C138: 120 | D138: Litros | E138: PR022 | F138: oregano | G138: 16 | H138: gramos
A139: SB011 | B139: CALDO BIRRIA | C139: 120 | D139: Litros | E139: PR023 | F139: pimienta blanca | G139: 16 | H139: gramos
...

Sheet Recetas.
A1: Codigo de Items | B1: Nombre de Items | C1: Codigo Producto | D1: Productos y Producciones | E1: Cantidad | F1: Unidad | G1: MARCA | H1: OBSERVACION
B2: Agua en Botella | C2: PEY27 | D2: Agua en botella | E2: 1 | F2: unidad | G2: TODAS
B3: Budweiser | C3: ='PRODUCTOS GENERALES PEYBU '!A29 -> PEY28 | D3: cerveza en lata | E3: 1 | F3: unidad | G3: TODAS
B4: Coca cola Normal | C4: PEY29 | D4: Gaseosa pet | E4: 1 | F4: unidad | G4: TODAS
B5: Coca cola Zero | C5: PEY29 | D5: Gaseosa pet | E5: 1 | F5: unidad | G5: TODAS
B6: Ginger | C6: PEY29 | D6: Gaseosa pet | E6: 1 | F6: unidad | G6: TODAS
A7: Bebida de la casa | B7: Horchata | C7: SUB016 | D7: horchata produccion | E7: 650 | F7: ml | G7: TODAS
B8: Horchata | C8: PEY41 | D8: Vasos 22 Oz gold | E8: 1 | F8: unidad | G8: TODAS
B9: Horchata | C9: PEY42 | D9: Tapas vaso Gold | E9: 1 | F9: unidad | G9: TODAS | H9: cuando es para llevar
A10: Bebida de la casa | B10: Jamaica | C10: SUB014 | D10: Jamaica produccion | E10: 650 | F10: ml | G10: TODAS
B11: Jamaica | C11: PEY41 | D11: Vasos 22 Oz gold | E11: 1 | F11: unidad | G11: TODAS
B12: Jamaica | C12: PEY42 | D12: Tapas vaso Gold | E12: 1 | F12: unidad | G12: TODAS | H12: cuando es para llevar
A13: Bebida de la casa | B13: Tamarindo | C13: SUB015 | D13: Tamarindo Producción | E13: 650 | F13: ml | G13: TODAS
B14: Tamarindo | C14: PEY41 | D14: Vasos 22 Oz gold | E14: 1 | F14: unidad | G14: TODAS
B15: Tamarindo | C15: PEY42 | D15: Tapas vaso Gold | E15: 1 | F15: unidad | G15: TODAS | H15: cuando es para llevar
A16: Bebida de la casa | B16: Michelada | C16: SUB07 | D16: Chamoy | E16: 27 | F16: gramos | G16: Rogelio red
B17: Michelada | C17: SUB08 | D17: Clamato | E17: 105 | F17: mililitros | G17: Rogelio red
B18: Michelada | C18: PEY24 | D18: sal de chamoy | E18: 4 | F18: gramos | G18: Rogelio red
B19: Michelada | C19: PEY18 | D19: Limón Taithy | E19: 25 | F19: gramos | G19: Rogelio red
B20: Michelada | C20: PEY22 | D20: Tabasco | E20: 0.5 | F20: mililitros | G20: Rogelio red
B21: Michelada | C21: PEY23 | D21: salsa ingelsa fresh | E21: 25 | F21: mililitros | G21: Rogelio red
B22: Michelada | C22: PEY41 | D22: Vasos 22 Oz gold | E22: 1 | F22: unidad | G22: Rogelio red
B23: Michelada | C23: PEY42 | D23: Tapas vaso Gold | E23: 1 | F23: unidad | G23: Rogelio red | H23: cuando es para llevar
B24: Michelada | C24: PEY26 | D24: Basukazo | E24: 1 | F24: unidad | G24: Rogelio red
B25: Michelada | C25: PEY25 | D25: Cerveza club colombia dorada 473 ml | E25: 1 | F25: unidad | G25: Rogelio red
A26: Adiciones | B26: Salsa picante | C26: PEY48 | D26: Scoop 2 onza carton | E26: 1 | F26: unidad | G26: Rogelio red
B27: Salsa picante | C27: PEY49 | D27: Tapa scoop 2 onzas | E27: 1 | F27: unidad | G27: Rogelio red | H27: cuando es para llevar
B28: Salsa picante | C28: SB002 | D28: SALSA PICANTE | E28: 45 | F28: mililitros | G28: Rogelio red
A29: Adiciones | B29: Porcion de tortilla | C29: PEY11 | D29: Tortillas Maíz 11x40 | E29: 3 | F29: unidad | G29: Rogelio red
B30: Porcion de tortilla | C30: PEY15 | D30: Tortillas fresca Maíz 11x32 autocar | E30: 3 | F30: unidad | G30: Autocar al pastor
B31: Adicion queso | C31: PEY80 | D31: Queso costeño | E31: 50 | F31: gramos | G31: ChayitoEsquites
B32: Adicion queso | C32: PEY48 | D32: Scoop 2 onza carton | E32: 1 | F32: unidad | G32: ChayitoEsquites
B33: Adicion queso | C33: PEY49 | D33: Tapa scoop 2 onzas | E33: 1 | F33: unidad | G33: ChayitoEsquites | H33: cuando es para llevar
B34: Adicion Chicharrón | C34: PR003 | D34: chicharrón | E34: 50 | F34: gramos | G34: ChayitoEsquites
B35: Adicion Chicharrón | C35: PEY48 | D35: Scoop 2 onza carton | E35: 1 | F35: unidad | G35: ChayitoEsquites
B36: Adicion Chicharrón | C36: PEY49 | D36: Tapa scoop 2 onzas | E36: 1 | F36: unidad | G36: ChayitoEsquites | H36: cuando es para llevar
B37: Caldo 8 onzas | C37: SB011 | D37: CALDO BIRRIA | E37: 240 | F37: mililitros | G37: Rogelio red
B38: Caldo 8 onzas | C38: PEY50 | D38: Sopero de 8 onzas carton | E38: 1 | F38: unidad | G38: Rogelio red
B39: Caldo 8 onzas | C39: PEY51 | D39: Tapa sopero 8 onzas | E39: 1 | F39: unidad | G39: Rogelio red
A40: Platos Principales | B40: vampiro | C40: PEY11 | D40: Tortillas Maíz 11x40 | E40: 1 | F40: unidad | G40: Rogelio red
B41: vampiro | C41: PEY81 | D41: queso mozarella | E41: 15 | F41: gramos | G41: Rogelio red
B42: vampiro | C42: SB010 | D42: BIRRIA ROGELIO | E42: 1 | F42: gramos | G42: Rogelio red
B43: vampiro | C43: PEY18 | D43: Limón Taithy | E43: 35 | F43: gramos | G43: Rogelio red
B44: vampiro | C44: SB001 | D44: SALSA TAQUERA ROGELIO | E44: 45 | F44: mililitros | G44: Rogelio red
B45: vampiro | C45: PEY48 | D45: Scoop 2 onza carton | E45: 1 | F45: unidad | G45: Rogelio red
B46: vampiro | C46: PEY49 | D46: Tapa scoop 2 onzas | E46: 1 | F46: unidad | G46: Rogelio red
B47: vampiro | C47: PEY43 | D47: Platos geo 23 cm Geopack | E47: 1 | F47: unidad | G47: Rogelio red
B48: vampiro | C48: PEY31 | D48: Papel parafinado | E48: 20 | F48: gramos | G48: Rogelio red
B49: vampiro | C49: PEY16 | D49: cebolla morada | E49: 5 | F49: gramos | G49: Rogelio red
B50: vampiro | C50: PEY17 | D50: Cilantro | E50: 5 | F50: gramos | G50: Rogelio red
B51: vampiro | C51: PEY32 | D51: Aluminio 300mt | E51: 0.23 | F51: unidad | G51: Rogelio red | H51: cuando es para llevar
B52: vampiro | C52: PEY34 | D52: Bolsa Camiseta 20 kilos | E52: 1 | F52: unidad | G52: Rogelio red | H52: cuando es para llevar
A53: Platos Principales | B53: Taco Rogelio | C53: PEY11 | D53: Tortillas Maíz 11x40 | E53: 2 | F53: unidad | G53: Rogelio red
B54: Taco Rogelio | C54: SB010 | D54: BIRRIA ROGELIO | E54: 20 | F54: gramos | G54: Rogelio red
B55: Taco Rogelio | C55: PEY18 | D55: Limón Taithy | E55: 35 | F55: gramos | G55: Rogelio red
B56: Taco Rogelio | C56: SB001 | D56: SALSA TAQUERA ROGELIO | E56: 45 | F56: mililitros | G56: Rogelio red
B57: Taco Rogelio | C57: PEY48 | D57: Scoop 2 onza carton | E57: 1 | F57: unidad | G57: Rogelio red
B58: Taco Rogelio | C58: PEY49 | D58: Tapa scoop 2 onzas | E58: 1 | F58: unidad | G58: Rogelio red
B59: Taco Rogelio | C59: PEY43 | D59: Platos geo 23 cm Geopack | E59: 1 | F59: unidad | G59: Rogelio red
B60: Taco Rogelio | C60: PEY31 | D60: Papel parafinado | E60: 1 | F60: gramos | G60: Rogelio red
B61: Taco Rogelio | C61: PEY16 | D61: cebolla morada | E61: 5 | F61: gramos | G61: Rogelio red
B62: Taco Rogelio | C62: PEY17 | D62: Cilantro | E62: 5 | F62: gramos | G62: Rogelio red
B63: Taco Rogelio | C63: PEY32 | D63: Aluminio 300mt | E63: 0.23 | F63: unidad | G63: Rogelio red | H63: cuando es para llevar
B64: Taco Rogelio | C64: PEY34 | D64: Bolsa Camiseta 20 kilos | E64: 1 | F64: unidad | G64: Rogelio red | H64: cuando es para llevar
A65: Platos Principales | B65: Mulita | C65: PEY11 | D65: Tortillas Maíz 11x40 | E65: 2 | F65: unidad | G65: Rogelio red
B66: Mulita | C66: PEY81 | D66: queso mozarella | E66: 15 | F66: gramos | G66: Rogelio red
B67: Mulita | C67: SB010 | D67: BIRRIA ROGELIO | E67: 20 | F67: gramos | G67: Rogelio red
B68: Mulita | C68: PEY18 | D68: Limón Taithy | E68: 35 | F68: gramos | G68: Rogelio red
B69: Mulita | C69: SB001 | D69: SALSA TAQUERA ROGELIO | E69: 45 | F69: mililitros | G69: Rogelio red
B70: Mulita | C70: PEY48 | D70: Scoop 2 onza carton | E70: 1 | F70: unidad | G70: Rogelio red
B71: Mulita | C71: PEY49 | D71: Tapa scoop 2 onzas | E71: 1 | F71: unidad | G71: Rogelio red
B72: Mulita | C72: PEY43 | D72: Platos geo 23 cm Geopack | E72: 1 | F72: unidad | G72: Rogelio red
B73: Mulita | C73: PEY31 | D73: Papel parafinado | E73: 1 | F73: gramos | G73: Rogelio red
B74: Mulita | C74: PEY16 | D74: cebolla morada | E74: 5 | F74: gramos | G74: Rogelio red
B75: Mulita | C75: PEY17 | D75: Cilantro | E75: 5 | F75: gramos | G75: Rogelio red
B76: Mulita | C76: PEY32 | D76: Aluminio 300mt | E76: 0.23 | F76: unidad | G76: Rogelio red | H76: cuando es para llevar
B77: Mulita | C77: PEY34 | D77: Bolsa Camiseta 20 kilos | E77: 1 | F77: unidad | G77: Rogelio red | H77: cuando es para llevar
A78: Platos Principales | B78: Lobita | C78: PEY11 | D78: Tortillas Maíz 11x40 | E78: 1 | F78: unidad | G78: Rogelio red
B79: Lobita | C79: SB010 | D79: BIRRIA ROGELIO | E79: 20 | F79: gramos | G79: Rogelio red
B80: Lobita | C80: PEY18 | D80: Limón Taithy | E80: 35 | F80: gramos | G80: Rogelio red
B81: Lobita | C81: SB001 | D81: SALSA TAQUERA ROGELIO | E81: 45 | F81: mililitros | G81: Rogelio red
B82: Lobita | C82: PEY48 | D82: Scoop 2 onza carton | E82: 1 | F82: unidad | G82: Rogelio red
B83: Lobita | C83: PEY49 | D83: Tapa scoop 2 onzas | E83: 1 | F83: unidad | G83: Rogelio red
B84: Lobita | C84: PEY43 | D84: Platos geo 23 cm Geopack | E84: 1 | F84: unidad | G84: Rogelio red
B85: Lobita | C85: PEY31 | D85: Papel parafinado | E85: 1 | F85: gramos | G85: Rogelio red
B86: Lobita | C86: PEY16 | D86: cebolla morada | E86: 5 | F86: gramos | G86: Rogelio red
B87: Lobita | C87: PEY17 | D87: Cilantro | E87: 5 | F87: gramos | G87: Rogelio red
B88: Lobita | C88: PEY32 | D88: Aluminio 300mt | E88: 0.23 | F88: unidad | G88: Rogelio red | H88: cuando es para llevar
B89: Lobita | C89: PEY34 | D89: Bolsa Camiseta 20 kilos | E89: 1 | F89: unidad | G89: Rogelio red | H89: cuando es para llevar
A90: Platos Principales | B90: Quesabirria | C90: PEY13 | D90: Tortillas Trigo 12 cm | E90: 1 | F90: unidad | G90: Rogelio red
B91: Quesabirria | C91: SB010 | D91: BIRRIA ROGELIO | E91: 35 | F91: gramos | G91: Rogelio red
B92: Quesabirria | C92: PEY81 | D92: queso mozarella | E92: 25 | F92: gramos | G92: Rogelio red
B93: Quesabirria | C93: PEY18 | D93: Limón Taithy | E93: 35 | F93: gramos | G93: Rogelio red
B94: Quesabirria | C94: SB001 | D94: SALSA TAQUERA ROGELIO | E94: 45 | F94: mililitros | G94: Rogelio red
B95: Quesabirria | C95: PEY48 | D95: Scoop 2 onza carton | E95: 1 | F95: unidad | G95: Rogelio red
B96: Quesabirria | C96: PEY49 | D96: Tapa scoop 2 onzas | E96: 1 | F96: unidad | G96: Rogelio red
B97: Quesabirria | C97: PEY43 | D97: Platos geo 23 cm Geopack | E97: 1 | F97: unidad | G97: Rogelio red
B98: Quesabirria | C98: PEY31 | D98: Papel parafinado | E98: 1 | F98: gramos | G98: Rogelio red
B99: Quesabirria | C99: PEY16 | D99: cebolla morada | E99: 5 | F99: gramos | G99: Rogelio red
B100: Quesabirria | C100: PEY17 | D100: Cilantro | E100: 5 | F100: gramos | G100: Rogelio red
...
